.coveragerc
.deepsource.toml
.editorconfig
.gitignore
.pre-commit-config.yaml
CHANGELOG.md
LICENSE
MANIFEST.in
README.md
conftest.py
environment.yml
pip_requirements.txt
pyproject.toml
pywwa_settings.json-example
.github/dependabot.yml
.github/workflows/build.yml
.github/workflows/codeql.yml
.github/workflows/etchosts.txt
examples/ADA.txt
examples/ADM.txt
examples/ADMNES.txt
examples/AFD.txt
examples/AQA.txt
examples/AQI.txt
examples/AVA.txt
examples/AVG.txt
examples/AVW.txt
examples/AWU.txt
examples/AWW.txt
examples/BLU.txt
examples/CAE.txt
examples/CEM.txt
examples/CF6.txt
examples/CFW.txt
examples/CGR.txt
examples/CLI.txt
examples/CLIANN.txt
examples/CLIHOU.txt
examples/CLM.txt
examples/CORM6.txt
examples/CORM6_RTP.txt
examples/CRF.txt
examples/CWA.txt
examples/CWF.txt
examples/CWFAER_0.txt
examples/CWFAER_1.txt
examples/CWFAER_2.txt
examples/DGT.txt
examples/DSM.txt
examples/EQI.txt
examples/EQR.txt
examples/ESF.txt
examples/EVI.txt
examples/EWW.txt
examples/FD1US1.txt
examples/FFA.txt
examples/FFGDMX.txt
examples/FFS.txt
examples/FFW.txt
examples/FFWPPG.txt
examples/FFWTWC_tilde.txt
examples/FLS.txt
examples/FLW.txt
examples/FRW.txt
examples/FRWOUN.txt
examples/FTM.txt
examples/FWA.txt
examples/FWF.txt
examples/FWS.txt
examples/GLF.txt
examples/HCM.txt
examples/HLS.txt
examples/HMD.txt
examples/HMLARX.txt
examples/HWO.txt
examples/HYD.txt
examples/ICE.txt
examples/LAE.txt
examples/LCO.txt
examples/LSR.txt
examples/LWGE86.txt
examples/MCD.txt
examples/METAR.txt
examples/METNC1.txt
examples/MIS.txt
examples/MPD.txt
examples/MWS.txt
examples/MWW.txt
examples/NCR_20121127_1413
examples/NCR_20200519_1950
examples/NCR_20210911_0023
examples/NOW.txt
examples/NOXX.txt
examples/NPW.txt
examples/NSH.txt
examples/OAV.txt
examples/OMR.txt
examples/PFM.txt
examples/PFWFD1.txt
examples/PFWFD2.txt
examples/PIREP.txt
examples/PNS.txt
examples/PNS_damage.txt
examples/PNS_damage_multi.txt
examples/PNS_damage_multi2.txt
examples/PSH.txt
examples/PTS.txt
examples/PTSDY1.txt
src/pywwa.egg-info/PKG-INFO
src/pywwa.egg-info/SOURCES.txt
src/pywwa.egg-info/dependency_links.txt
src/pywwa.egg-info/entry_points.txt
src/pywwa.egg-info/requires.txt
src/pywwa.egg-info/top_level.txt
